toponymy/__init__.py
toponymy/_utils.py
toponymy/audit.py
toponymy/cluster_layer.py
toponymy/clustering.py
toponymy/embedding_wrappers.py
toponymy/exemplar_texts.py
toponymy/keyphrases.py
toponymy/llm_wrappers.py
toponymy/plotting.py
toponymy/prompt_construction.py
toponymy/subtopics.py
toponymy/templates.py
toponymy/topic_tree.py
toponymy/toponymy.py
toponymy/utility_functions.py
toponymy/widgets/circlePacking/dist/widget.css
toponymy/widgets/circlePacking/dist/widget.js
toponymy/widgets/indentedTree/dist/widget.css
toponymy/widgets/indentedTree/dist/widget.js
toponymy/widgets/radialTidyTree/dist/widget.css
toponymy/widgets/radialTidyTree/dist/widget.js
toponymy-0.4.0.dist-info/LICENSE
toponymy-0.4.0.dist-info/METADATA
toponymy-0.4.0.dist-info/WHEEL
toponymy-0.4.0.dist-info/top_level.txt
toponymy-0.4.0.dist-info/RECORD
