Metadata-Version: 2.1
Name: toponymy
Version: 0.4.0
Summary: A library for using large language models to name topics
Home-page: https://github.com/TutteInstitute/toponymy
Author: John Healy, Leland McInnes
Author-email: jchealy@gmail.com, leland.mcinnes@gmail.com
Maintainer: John Healy, Leland McInnes
Maintainer-email: jchealy@gmail.com, leland.mcinnes@gmail.com
License: MIT License
Keywords: topic modeing,representation,cluster,clustering,large language models,LLM,topic naming
Classifier: License :: OSI Approved :: MIT License
Classifier: Programming Language :: Python :: 3.9
Classifier: Programming Language :: Python :: 3.10
Classifier: Development Status :: 4 - Beta
Classifier: Operating System :: OS Independent
Requires-Python: >=3.9
License-File: LICENSE
Requires-Dist: numpy>=1.21
Requires-Dist: pandas>=1.0
Requires-Dist: numba>=0.56
Requires-Dist: datasets
Requires-Dist: scikit-learn>=1.6
Requires-Dist: vectorizers
Requires-Dist: scipy
Requires-Dist: fast-hdbscan>=0.2.2
Requires-Dist: dataclasses
Requires-Dist: tqdm
Requires-Dist: tenacity
Requires-Dist: httpx
Requires-Dist: apricot-select
Provides-Extra: dev
Requires-Dist: black; extra == "dev"
Requires-Dist: isort; extra == "dev"
Requires-Dist: pylint; extra == "dev"
Requires-Dist: pytest; extra == "dev"
Requires-Dist: anthropic; extra == "dev"
Requires-Dist: cohere; extra == "dev"
Requires-Dist: azure-ai-inference; extra == "dev"
Requires-Dist: llama-cpp-python; extra == "dev"
Requires-Dist: openai; extra == "dev"
Requires-Dist: transformers; extra == "dev"
Requires-Dist: bm25s; extra == "dev"
Requires-Dist: anywidget; extra == "dev"
Requires-Dist: traitlets; extra == "dev"
